{
  "seen_ids": [
    "1066",
    "1447",
    "867",
    "712",
    "266",
    "1645",
    "698",
    "1538",
    "2052",
    "1120",
    "1269",
    "1004",
    "2055",
    "80",
    "360",
    "862",
    "650",
    "1564",
    "984",
    "2803",
    "389",
    "890",
    "2598",
    "137",
    "348",
    "509",
    "734",
    "1631",
    "2468",
    "154",
    "993",
    "964",
    "1712",
    "1017",
    "1880",
    "2819",
    "891",
    "1859",
    "1388",
    "3003",
    "1141",
    "303",
    "786",
    "2000",
    "10",
    "305",
    "1858",
    "2814",
    "665",
    "3238",
    "3002",
    "3164",
    "983",
    "1780",
    "3150",
    "1904",
    "443",
    "889",
    "2213",
    "119",
    "913",
    "778",
    "642",
    "909",
    "517",
    "1042",
    "761",
    "1751",
    "238",
    "2612",
    "3187",
    "388",
    "3188",
    "1019",
    "368",
    "1343",
    "1219",
    "334",
    "792",
    "404",
    "789",
    "1662",
    "724",
    "1776",
    "3151",
    "1252",
    "1034",
    "1529",
    "678",
    "3153",
    "2928",
    "1663",
    "1022",
    "2419",
    "2867",
    "1039",
    "696",
    "1671",
    "1685",
    "622",
    "1092",
    "3222",
    "3023",
    "1065",
    "2815",
    "283",
    "816",
    "3206",
    "756",
    "965",
    "2456",
    "1054",
    "985",
    "1418",
    "1755",
    "661",
    "908",
    "3183",
    "697",
    "226",
    "2149",
    "1701",
    "802",
    "317",
    "1229",
    "1046",
    "1594",
    "1652",
    "535",
    "2997",
    "673",
    "2980",
    "1849",
    "3119",
    "948",
    "1591",
    "1127",
    "60",
    "585",
    "2439",
    "812",
    "3239",
    "353",
    "2131",
    "647",
    "2609",
    "240",
    "840",
    "854",
    "2605",
    "671",
    "3004",
    "1754",
    "258",
    "1031",
    "2402",
    "3236",
    "187",
    "1909",
    "1925",
    "836",
    "3215",
    "763",
    "3152",
    "3139",
    "1897",
    "1716",
    "733",
    "3120",
    "466",
    "936",
    "955",
    "2866",
    "1270",
    "1619",
    "875",
    "2790",
    "2593",
    "1808",
    "928",
    "922",
    "3189",
    "2116",
    "3190",
    "1484",
    "1731",
    "1310",
    "1465",
    "169",
    "2873",
    "3140",
    "1915",
    "1498",
    "3252",
    "2042",
    "1584",
    "1501",
    "1917",
    "3186",
    "3273",
    "1428",
    "634",
    "3182",
    "900"
  ],
  "last_total_matching": 149,
  "last_success": "2026-07-05 11:51:30",
  "light_signature": {
    "total_pages": 60,
    "page1_ids": [
      "1301",
      "1305",
      "1306",
      "1307",
      "1310",
      "1311",
      "1314",
      "1315",
      "1316",
      "1317",
      "1319",
      "1320",
      "1324",
      "1326",
      "1327",
      "1328",
      "1331",
      "1332",
      "1333",
      "1336",
      "1341",
      "1343",
      "1347",
      "1348"
    ]
  }
}